{
  "openapi": "3.0.3",
  "info": {
    "title": "Routine Cloud API v1",
    "description": "Routine Cloud API SDK",
    "version": "v1"
  },
  "paths": {
    "/api/devices/": {
      "get": {
        "tags": [
          "devices"
        ],
        "summary": "List Devices",
        "description": "Return all devices that belong to the authenticated user.",
        "operationId": "devices_list",
        "security": [
          {
            "OAuth2PasswordBearer": []
          }
        ],
        "parameters": [
          {
            "name": "X-ID-Token",
            "in": "header",
            "required": false,
            "schema": {
              "title": "X-Id-Token",
              "type": "string",
              "nullable": true
            }
          }
        ],
        "responses": {
          "200": {
            "description": "Successful Response",
            "content": {
              "application/json": {
                "schema": {
                  "type": "array",
                  "items": {
                    "$ref": "#/components/schemas/DeviceRead"
                  },
                  "title": "Response Devices List"
                }
              }
            }
          },
          "404": {
            "description": "Not found"
          },
          "422": {
            "description": "Validation Error",
            "content": {
              "application/json": {
                "schema": {
                  "$ref": "#/components/schemas/HTTPValidationError"
                }
              }
            }
          }
        }
      }
    },
    "/api/devices/{device_id}": {
      "get": {
        "tags": [
          "devices"
        ],
        "summary": "Get Device",
        "description": "Return a single device by ID if it belongs to the authenticated user.",
        "operationId": "devices_get",
        "security": [
          {
            "OAuth2PasswordBearer": []
          }
        ],
        "parameters": [
          {
            "name": "device_id",
            "in": "path",
            "required": true,
            "schema": {
              "type": "integer",
              "title": "Device Id"
            }
          },
          {
            "name": "X-ID-Token",
            "in": "header",
            "required": false,
            "schema": {
              "title": "X-Id-Token",
              "type": "string",
              "nullable": true
            }
          }
        ],
        "responses": {
          "200": {
            "description": "Successful Response",
            "content": {
              "application/json": {
                "schema": {
                  "$ref": "#/components/schemas/DeviceRead"
                }
              }
            }
          },
          "404": {
            "description": "Not found"
          },
          "422": {
            "description": "Validation Error",
            "content": {
              "application/json": {
                "schema": {
                  "$ref": "#/components/schemas/HTTPValidationError"
                }
              }
            }
          }
        }
      }
    },
    "/api/users/me": {
      "get": {
        "tags": [
          "users"
        ],
        "summary": "Get Current User Me",
        "description": "Get current user information and sync with OIDC",
        "operationId": "users_me",
        "security": [
          {
            "OAuth2PasswordBearer": []
          }
        ],
        "parameters": [
          {
            "name": "X-ID-Token",
            "in": "header",
            "required": false,
            "schema": {
              "title": "X-Id-Token",
              "type": "string",
              "nullable": true
            }
          }
        ],
        "responses": {
          "200": {
            "description": "Successful Response",
            "content": {
              "application/json": {
                "schema": {
                  "$ref": "#/components/schemas/UserRead"
                }
              }
            }
          },
          "404": {
            "description": "Not found"
          },
          "422": {
            "description": "Validation Error",
            "content": {
              "application/json": {
                "schema": {
                  "$ref": "#/components/schemas/HTTPValidationError"
                }
              }
            }
          }
        }
      },
      "patch": {
        "tags": [
          "users"
        ],
        "summary": "Update Current User Me",
        "description": "Update current user profile (profile picture)",
        "operationId": "users_update_me",
        "security": [
          {
            "OAuth2PasswordBearer": []
          }
        ],
        "parameters": [
          {
            "name": "X-ID-Token",
            "in": "header",
            "required": false,
            "schema": {
              "title": "X-Id-Token",
              "type": "string",
              "nullable": true
            }
          }
        ],
        "requestBody": {
          "required": true,
          "content": {
            "application/json": {
              "schema": {
                "$ref": "#/components/schemas/UserUpdate"
              }
            }
          }
        },
        "responses": {
          "200": {
            "description": "Successful Response",
            "content": {
              "application/json": {
                "schema": {
                  "$ref": "#/components/schemas/UserRead"
                }
              }
            }
          },
          "404": {
            "description": "Not found"
          },
          "422": {
            "description": "Validation Error",
            "content": {
              "application/json": {
                "schema": {
                  "$ref": "#/components/schemas/HTTPValidationError"
                }
              }
            }
          }
        }
      }
    },
    "/api/users/": {
      "get": {
        "tags": [
          "users"
        ],
        "summary": "List Users",
        "description": "List all users.",
        "operationId": "users_list",
        "security": [
          {
            "OAuth2PasswordBearer": []
          }
        ],
        "parameters": [
          {
            "name": "X-ID-Token",
            "in": "header",
            "required": false,
            "schema": {
              "title": "X-Id-Token",
              "type": "string",
              "nullable": true
            }
          }
        ],
        "responses": {
          "200": {
            "description": "Successful Response",
            "content": {
              "application/json": {
                "schema": {
                  "type": "array",
                  "items": {
                    "$ref": "#/components/schemas/UserRead"
                  },
                  "title": "Response Users List"
                }
              }
            }
          },
          "404": {
            "description": "Not found"
          },
          "422": {
            "description": "Validation Error",
            "content": {
              "application/json": {
                "schema": {
                  "$ref": "#/components/schemas/HTTPValidationError"
                }
              }
            }
          }
        }
      }
    },
    "/api/tasks/": {
      "get": {
        "tags": [
          "tasks"
        ],
        "summary": "List My Tasks",
        "description": "List all tasks owned by the current user.",
        "operationId": "tasks_list",
        "security": [
          {
            "OAuth2PasswordBearer": []
          }
        ],
        "parameters": [
          {
            "name": "X-ID-Token",
            "in": "header",
            "required": false,
            "schema": {
              "title": "X-Id-Token",
              "type": "string",
              "nullable": true
            }
          }
        ],
        "responses": {
          "200": {
            "description": "Successful Response",
            "content": {
              "application/json": {
                "schema": {
                  "type": "array",
                  "items": {
                    "$ref": "#/components/schemas/TaskRead"
                  },
                  "title": "Response Tasks List"
                }
              }
            }
          },
          "422": {
            "description": "Validation Error",
            "content": {
              "application/json": {
                "schema": {
                  "$ref": "#/components/schemas/HTTPValidationError"
                }
              }
            }
          }
        }
      },
      "post": {
        "tags": [
          "tasks"
        ],
        "summary": "Create Task",
        "description": "Create a new task owned by the current user. Returns the created task.",
        "operationId": "tasks_create",
        "security": [
          {
            "OAuth2PasswordBearer": []
          }
        ],
        "parameters": [
          {
            "name": "X-ID-Token",
            "in": "header",
            "required": false,
            "schema": {
              "title": "X-Id-Token",
              "type": "string",
              "nullable": true
            }
          }
        ],
        "requestBody": {
          "required": true,
          "content": {
            "application/json": {
              "schema": {
                "$ref": "#/components/schemas/TaskCreate"
              }
            }
          }
        },
        "responses": {
          "201": {
            "description": "Successful Response",
            "content": {
              "application/json": {
                "schema": {
                  "$ref": "#/components/schemas/TaskRead"
                }
              }
            }
          },
          "422": {
            "description": "Validation Error",
            "content": {
              "application/json": {
                "schema": {
                  "$ref": "#/components/schemas/HTTPValidationError"
                }
              }
            }
          }
        }
      }
    },
    "/api/tasks/{task_id}": {
      "patch": {
        "tags": [
          "tasks"
        ],
        "summary": "Update Task",
        "description": "Update mutable fields of a task. All fields are optional; only provided fields are updated.",
        "operationId": "tasks_update",
        "security": [
          {
            "OAuth2PasswordBearer": []
          }
        ],
        "parameters": [
          {
            "name": "task_id",
            "in": "path",
            "required": true,
            "schema": {
              "type": "integer",
              "title": "Task Id"
            }
          },
          {
            "name": "X-ID-Token",
            "in": "header",
            "required": false,
            "schema": {
              "title": "X-Id-Token",
              "type": "string",
              "nullable": true
            }
          }
        ],
        "requestBody": {
          "required": true,
          "content": {
            "application/json": {
              "schema": {
                "$ref": "#/components/schemas/TaskUpdate"
              }
            }
          }
        },
        "responses": {
          "200": {
            "description": "Successful Response",
            "content": {
              "application/json": {
                "schema": {
                  "$ref": "#/components/schemas/TaskRead"
                }
              }
            }
          },
          "422": {
            "description": "Validation Error",
            "content": {
              "application/json": {
                "schema": {
                  "$ref": "#/components/schemas/HTTPValidationError"
                }
              }
            }
          }
        }
      },
      "delete": {
        "tags": [
          "tasks"
        ],
        "summary": "Delete Task",
        "description": "Delete a task only if you are its owner and it is not used in routines owned by other users.",
        "operationId": "tasks_delete",
        "security": [
          {
            "OAuth2PasswordBearer": []
          }
        ],
        "parameters": [
          {
            "name": "task_id",
            "in": "path",
            "required": true,
            "schema": {
              "type": "integer",
              "title": "Task Id"
            }
          },
          {
            "name": "X-ID-Token",
            "in": "header",
            "required": false,
            "schema": {
              "title": "X-Id-Token",
              "type": "string",
              "nullable": true
            }
          }
        ],
        "responses": {
          "204": {
            "description": "Successful Response"
          },
          "422": {
            "description": "Validation Error",
            "content": {
              "application/json": {
                "schema": {
                  "$ref": "#/components/schemas/HTTPValidationError"
                }
              }
            }
          }
        }
      }
    },
    "/api/routines/": {
      "post": {
        "tags": [
          "routines"
        ],
        "summary": "Create Routine",
        "operationId": "routines_create",
        "security": [
          {
            "OAuth2PasswordBearer": []
          }
        ],
        "parameters": [
          {
            "name": "X-ID-Token",
            "in": "header",
            "required": false,
            "schema": {
              "title": "X-Id-Token",
              "type": "string",
              "nullable": true
            }
          }
        ],
        "requestBody": {
          "required": true,
          "content": {
            "application/json": {
              "schema": {
                "$ref": "#/components/schemas/RoutineCreate"
              }
            }
          }
        },
        "responses": {
          "201": {
            "description": "Successful Response",
            "content": {
              "application/json": {
                "schema": {
                  "$ref": "#/components/schemas/RoutineRead"
                }
              }
            }
          },
          "422": {
            "description": "Validation Error",
            "content": {
              "application/json": {
                "schema": {
                  "$ref": "#/components/schemas/HTTPValidationError"
                }
              }
            }
          }
        }
      },
      "get": {
        "tags": [
          "routines"
        ],
        "summary": "List Routines",
        "operationId": "routines_list",
        "security": [
          {
            "OAuth2PasswordBearer": []
          }
        ],
        "parameters": [
          {
            "name": "include_tasks",
            "in": "query",
            "required": false,
            "schema": {
              "type": "boolean",
              "description": "Include tasks for each routine",
              "default": false,
              "title": "Include Tasks"
            },
            "description": "Include tasks for each routine"
          },
          {
            "name": "X-ID-Token",
            "in": "header",
            "required": false,
            "schema": {
              "title": "X-Id-Token",
              "type": "string",
              "nullable": true
            }
          }
        ],
        "responses": {
          "200": {
            "description": "Successful Response",
            "content": {
              "application/json": {
                "schema": {
                  "type": "array",
                  "items": {
                    "$ref": "#/components/schemas/RoutineRead"
                  },
                  "title": "Response Routines List"
                }
              }
            }
          },
          "422": {
            "description": "Validation Error",
            "content": {
              "application/json": {
                "schema": {
                  "$ref": "#/components/schemas/HTTPValidationError"
                }
              }
            }
          }
        }
      }
    },
    "/api/routines/active/status": {
      "get": {
        "tags": [
          "routines"
        ],
        "summary": "Active Status",
        "operationId": "routines_active_status",
        "security": [
          {
            "OAuth2PasswordBearer": []
          }
        ],
        "parameters": [
          {
            "name": "X-ID-Token",
            "in": "header",
            "required": false,
            "schema": {
              "title": "X-Id-Token",
              "type": "string",
              "nullable": true
            }
          }
        ],
        "responses": {
          "200": {
            "description": "Successful Response",
            "content": {
              "application/json": {
                "schema": {
                  "$ref": "#/components/schemas/ActiveRoutineStatusRead"
                }
              }
            }
          },
          "422": {
            "description": "Validation Error",
            "content": {
              "application/json": {
                "schema": {
                  "$ref": "#/components/schemas/HTTPValidationError"
                }
              }
            }
          }
        }
      }
    },
    "/api/routines/active/skip": {
      "post": {
        "tags": [
          "routines"
        ],
        "summary": "Skip Active Task",
        "operationId": "routines_active_skip",
        "security": [
          {
            "OAuth2PasswordBearer": []
          }
        ],
        "parameters": [
          {
            "name": "X-ID-Token",
            "in": "header",
            "required": false,
            "schema": {
              "title": "X-Id-Token",
              "type": "string",
              "nullable": true
            }
          }
        ],
        "responses": {
          "202": {
            "description": "Successful Response",
            "content": {
              "application/json": {
                "schema": {}
              }
            }
          },
          "422": {
            "description": "Validation Error",
            "content": {
              "application/json": {
                "schema": {
                  "$ref": "#/components/schemas/HTTPValidationError"
                }
              }
            }
          }
        }
      }
    },
    "/api/routines/active/pause": {
      "post": {
        "tags": [
          "routines"
        ],
        "summary": "Pause Active Routine",
        "operationId": "routines_active_pause",
        "security": [
          {
            "OAuth2PasswordBearer": []
          }
        ],
        "parameters": [
          {
            "name": "X-ID-Token",
            "in": "header",
            "required": false,
            "schema": {
              "title": "X-Id-Token",
              "type": "string",
              "nullable": true
            }
          }
        ],
        "responses": {
          "202": {
            "description": "Successful Response",
            "content": {
              "application/json": {
                "schema": {}
              }
            }
          },
          "422": {
            "description": "Validation Error",
            "content": {
              "application/json": {
                "schema": {
                  "$ref": "#/components/schemas/HTTPValidationError"
                }
              }
            }
          }
        }
      }
    },
    "/api/routines/active/resume": {
      "post": {
        "tags": [
          "routines"
        ],
        "summary": "Resume Active Routine",
        "operationId": "routines_active_resume",
        "security": [
          {
            "OAuth2PasswordBearer": []
          }
        ],
        "parameters": [
          {
            "name": "X-ID-Token",
            "in": "header",
            "required": false,
            "schema": {
              "title": "X-Id-Token",
              "type": "string",
              "nullable": true
            }
          }
        ],
        "responses": {
          "202": {
            "description": "Successful Response",
            "content": {
              "application/json": {
                "schema": {}
              }
            }
          },
          "422": {
            "description": "Validation Error",
            "content": {
              "application/json": {
                "schema": {
                  "$ref": "#/components/schemas/HTTPValidationError"
                }
              }
            }
          }
        }
      }
    },
    "/api/routines/{routine_id}": {
      "get": {
        "tags": [
          "routines"
        ],
        "summary": "Get Routine",
        "operationId": "routines_get",
        "security": [
          {
            "OAuth2PasswordBearer": []
          }
        ],
        "parameters": [
          {
            "name": "routine_id",
            "in": "path",
            "required": true,
            "schema": {
              "type": "integer",
              "title": "Routine Id"
            }
          },
          {
            "name": "X-ID-Token",
            "in": "header",
            "required": false,
            "schema": {
              "title": "X-Id-Token",
              "type": "string",
              "nullable": true
            }
          }
        ],
        "responses": {
          "200": {
            "description": "Successful Response",
            "content": {
              "application/json": {
                "schema": {
                  "$ref": "#/components/schemas/RoutineRead"
                }
              }
            }
          },
          "422": {
            "description": "Validation Error",
            "content": {
              "application/json": {
                "schema": {
                  "$ref": "#/components/schemas/HTTPValidationError"
                }
              }
            }
          }
        }
      },
      "patch": {
        "tags": [
          "routines"
        ],
        "summary": "Update Routine",
        "operationId": "routines_update",
        "security": [
          {
            "OAuth2PasswordBearer": []
          }
        ],
        "parameters": [
          {
            "name": "routine_id",
            "in": "path",
            "required": true,
            "schema": {
              "type": "integer",
              "title": "Routine Id"
            }
          },
          {
            "name": "X-ID-Token",
            "in": "header",
            "required": false,
            "schema": {
              "title": "X-Id-Token",
              "type": "string",
              "nullable": true
            }
          }
        ],
        "requestBody": {
          "required": true,
          "content": {
            "application/json": {
              "schema": {
                "$ref": "#/components/schemas/RoutineUpdate"
              }
            }
          }
        },
        "responses": {
          "200": {
            "description": "Successful Response",
            "content": {
              "application/json": {
                "schema": {
                  "$ref": "#/components/schemas/RoutineRead"
                }
              }
            }
          },
          "422": {
            "description": "Validation Error",
            "content": {
              "application/json": {
                "schema": {
                  "$ref": "#/components/schemas/HTTPValidationError"
                }
              }
            }
          }
        }
      },
      "delete": {
        "tags": [
          "routines"
        ],
        "summary": "Delete Routine",
        "operationId": "routines_delete",
        "security": [
          {
            "OAuth2PasswordBearer": []
          }
        ],
        "parameters": [
          {
            "name": "routine_id",
            "in": "path",
            "required": true,
            "schema": {
              "type": "integer",
              "title": "Routine Id"
            }
          },
          {
            "name": "X-ID-Token",
            "in": "header",
            "required": false,
            "schema": {
              "title": "X-Id-Token",
              "type": "string",
              "nullable": true
            }
          }
        ],
        "responses": {
          "204": {
            "description": "Successful Response"
          },
          "422": {
            "description": "Validation Error",
            "content": {
              "application/json": {
                "schema": {
                  "$ref": "#/components/schemas/HTTPValidationError"
                }
              }
            }
          }
        }
      }
    },
    "/api/routines/{routine_id}/tasks": {
      "get": {
        "tags": [
          "routines"
        ],
        "summary": "List Routine Tasks",
        "operationId": "routines_tasks_list",
        "security": [
          {
            "OAuth2PasswordBearer": []
          }
        ],
        "parameters": [
          {
            "name": "routine_id",
            "in": "path",
            "required": true,
            "schema": {
              "type": "integer",
              "title": "Routine Id"
            }
          },
          {
            "name": "X-ID-Token",
            "in": "header",
            "required": false,
            "schema": {
              "title": "X-Id-Token",
              "type": "string",
              "nullable": true
            }
          }
        ],
        "responses": {
          "200": {
            "description": "Successful Response",
            "content": {
              "application/json": {
                "schema": {
                  "type": "array",
                  "items": {
                    "$ref": "#/components/schemas/TaskInRoutineRead"
                  },
                  "title": "Response Routines Tasks List"
                }
              }
            }
          },
          "422": {
            "description": "Validation Error",
            "content": {
              "application/json": {
                "schema": {
                  "$ref": "#/components/schemas/HTTPValidationError"
                }
              }
            }
          }
        }
      },
      "post": {
        "tags": [
          "routines"
        ],
        "summary": "Add Task To Routine",
        "operationId": "routines_tasks_add",
        "security": [
          {
            "OAuth2PasswordBearer": []
          }
        ],
        "parameters": [
          {
            "name": "routine_id",
            "in": "path",
            "required": true,
            "schema": {
              "type": "integer",
              "title": "Routine Id"
            }
          },
          {
            "name": "X-ID-Token",
            "in": "header",
            "required": false,
            "schema": {
              "title": "X-Id-Token",
              "type": "string",
              "nullable": true
            }
          }
        ],
        "requestBody": {
          "required": true,
          "content": {
            "application/json": {
              "schema": {
                "$ref": "#/components/schemas/RoutineTaskAdd"
              }
            }
          }
        },
        "responses": {
          "201": {
            "description": "Successful Response",
            "content": {
              "application/json": {
                "schema": {
                  "type": "array",
                  "items": {
                    "$ref": "#/components/schemas/TaskInRoutineRead"
                  },
                  "title": "Response Routines Tasks Add"
                }
              }
            }
          },
          "422": {
            "description": "Validation Error",
            "content": {
              "application/json": {
                "schema": {
                  "$ref": "#/components/schemas/HTTPValidationError"
                }
              }
            }
          }
        }
      }
    },
    "/api/routines/{routine_id}/tasks/{position}": {
      "delete": {
        "tags": [
          "routines"
        ],
        "summary": "Remove Task From Routine",
        "operationId": "routines_tasks_remove",
        "security": [
          {
            "OAuth2PasswordBearer": []
          }
        ],
        "parameters": [
          {
            "name": "routine_id",
            "in": "path",
            "required": true,
            "schema": {
              "type": "integer",
              "title": "Routine Id"
            }
          },
          {
            "name": "position",
            "in": "path",
            "required": true,
            "schema": {
              "type": "integer",
              "title": "Position"
            }
          },
          {
            "name": "X-ID-Token",
            "in": "header",
            "required": false,
            "schema": {
              "title": "X-Id-Token",
              "type": "string",
              "nullable": true
            }
          }
        ],
        "responses": {
          "200": {
            "description": "Successful Response",
            "content": {
              "application/json": {
                "schema": {
                  "type": "array",
                  "items": {
                    "$ref": "#/components/schemas/TaskInRoutineRead"
                  },
                  "title": "Response Routines Tasks Remove"
                }
              }
            }
          },
          "422": {
            "description": "Validation Error",
            "content": {
              "application/json": {
                "schema": {
                  "$ref": "#/components/schemas/HTTPValidationError"
                }
              }
            }
          }
        }
      }
    },
    "/api/routines/{routine_id}/start": {
      "post": {
        "tags": [
          "routines"
        ],
        "summary": "Start Routine",
        "operationId": "routines_start",
        "security": [
          {
            "OAuth2PasswordBearer": []
          }
        ],
        "parameters": [
          {
            "name": "routine_id",
            "in": "path",
            "required": true,
            "schema": {
              "type": "integer",
              "title": "Routine Id"
            }
          },
          {
            "name": "X-ID-Token",
            "in": "header",
            "required": false,
            "schema": {
              "title": "X-Id-Token",
              "type": "string",
              "nullable": true
            }
          }
        ],
        "responses": {
          "202": {
            "description": "Successful Response",
            "content": {
              "application/json": {
                "schema": {}
              }
            }
          },
          "422": {
            "description": "Validation Error",
            "content": {
              "application/json": {
                "schema": {
                  "$ref": "#/components/schemas/HTTPValidationError"
                }
              }
            }
          }
        }
      }
    },
    "/api/routines/{routine_id}/shares": {
      "post": {
        "tags": [
          "routines"
        ],
        "summary": "Create Routine Share",
        "operationId": "routines_shares_create",
        "security": [
          {
            "OAuth2PasswordBearer": []
          }
        ],
        "parameters": [
          {
            "name": "routine_id",
            "in": "path",
            "required": true,
            "schema": {
              "type": "integer",
              "title": "Routine Id"
            }
          },
          {
            "name": "X-ID-Token",
            "in": "header",
            "required": false,
            "schema": {
              "title": "X-Id-Token",
              "type": "string",
              "nullable": true
            }
          }
        ],
        "requestBody": {
          "required": true,
          "content": {
            "application/json": {
              "schema": {
                "$ref": "#/components/schemas/RoutineShareCreate"
              }
            }
          }
        },
        "responses": {
          "201": {
            "description": "Successful Response",
            "content": {
              "application/json": {
                "schema": {
                  "$ref": "#/components/schemas/RoutineShareRead"
                }
              }
            }
          },
          "422": {
            "description": "Validation Error",
            "content": {
              "application/json": {
                "schema": {
                  "$ref": "#/components/schemas/HTTPValidationError"
                }
              }
            }
          }
        }
      },
      "get": {
        "tags": [
          "routines"
        ],
        "summary": "List Routine Shares",
        "operationId": "routines_shares_list",
        "security": [
          {
            "OAuth2PasswordBearer": []
          }
        ],
        "parameters": [
          {
            "name": "routine_id",
            "in": "path",
            "required": true,
            "schema": {
              "type": "integer",
              "title": "Routine Id"
            }
          },
          {
            "name": "X-ID-Token",
            "in": "header",
            "required": false,
            "schema": {
              "title": "X-Id-Token",
              "type": "string",
              "nullable": true
            }
          }
        ],
        "responses": {
          "200": {
            "description": "Successful Response",
            "content": {
              "application/json": {
                "schema": {
                  "type": "array",
                  "items": {
                    "$ref": "#/components/schemas/RoutineShareRead"
                  },
                  "title": "Response Routines Shares List"
                }
              }
            }
          },
          "422": {
            "description": "Validation Error",
            "content": {
              "application/json": {
                "schema": {
                  "$ref": "#/components/schemas/HTTPValidationError"
                }
              }
            }
          }
        }
      }
    },
    "/api/routines/{routine_id}/shares/{user_id}": {
      "get": {
        "tags": [
          "routines"
        ],
        "summary": "Get Routine Share",
        "operationId": "routines_shares_get",
        "security": [
          {
            "OAuth2PasswordBearer": []
          }
        ],
        "parameters": [
          {
            "name": "routine_id",
            "in": "path",
            "required": true,
            "schema": {
              "type": "integer",
              "title": "Routine Id"
            }
          },
          {
            "name": "user_id",
            "in": "path",
            "required": true,
            "schema": {
              "type": "integer",
              "title": "User Id"
            }
          },
          {
            "name": "X-ID-Token",
            "in": "header",
            "required": false,
            "schema": {
              "title": "X-Id-Token",
              "type": "string",
              "nullable": true
            }
          }
        ],
        "responses": {
          "200": {
            "description": "Successful Response",
            "content": {
              "application/json": {
                "schema": {
                  "$ref": "#/components/schemas/RoutineShareRead"
                }
              }
            }
          },
          "422": {
            "description": "Validation Error",
            "content": {
              "application/json": {
                "schema": {
                  "$ref": "#/components/schemas/HTTPValidationError"
                }
              }
            }
          }
        }
      },
      "patch": {
        "tags": [
          "routines"
        ],
        "summary": "Update Routine Share",
        "operationId": "routines_shares_update",
        "security": [
          {
            "OAuth2PasswordBearer": []
          }
        ],
        "parameters": [
          {
            "name": "routine_id",
            "in": "path",
            "required": true,
            "schema": {
              "type": "integer",
              "title": "Routine Id"
            }
          },
          {
            "name": "user_id",
            "in": "path",
            "required": true,
            "schema": {
              "type": "integer",
              "title": "User Id"
            }
          },
          {
            "name": "X-ID-Token",
            "in": "header",
            "required": false,
            "schema": {
              "title": "X-Id-Token",
              "type": "string",
              "nullable": true
            }
          }
        ],
        "requestBody": {
          "required": true,
          "content": {
            "application/json": {
              "schema": {
                "$ref": "#/components/schemas/RoutineShareUpdate"
              }
            }
          }
        },
        "responses": {
          "200": {
            "description": "Successful Response",
            "content": {
              "application/json": {
                "schema": {
                  "$ref": "#/components/schemas/RoutineShareRead"
                }
              }
            }
          },
          "422": {
            "description": "Validation Error",
            "content": {
              "application/json": {
                "schema": {
                  "$ref": "#/components/schemas/HTTPValidationError"
                }
              }
            }
          }
        }
      },
      "delete": {
        "tags": [
          "routines"
        ],
        "summary": "Delete Routine Share",
        "operationId": "routines_shares_delete",
        "security": [
          {
            "OAuth2PasswordBearer": []
          }
        ],
        "parameters": [
          {
            "name": "routine_id",
            "in": "path",
            "required": true,
            "schema": {
              "type": "integer",
              "title": "Routine Id"
            }
          },
          {
            "name": "user_id",
            "in": "path",
            "required": true,
            "schema": {
              "type": "integer",
              "title": "User Id"
            }
          },
          {
            "name": "X-ID-Token",
            "in": "header",
            "required": false,
            "schema": {
              "title": "X-Id-Token",
              "type": "string",
              "nullable": true
            }
          }
        ],
        "responses": {
          "204": {
            "description": "Successful Response"
          },
          "422": {
            "description": "Validation Error",
            "content": {
              "application/json": {
                "schema": {
                  "$ref": "#/components/schemas/HTTPValidationError"
                }
              }
            }
          }
        }
      }
    },
    "/api/routine-control/start": {
      "post": {
        "tags": [
          "routine-control"
        ],
        "summary": "Start Routine By Name",
        "operationId": "start_routine_by_name_api_routine_control_start_post",
        "security": [
          {
            "OAuth2PasswordBearer": []
          }
        ],
        "parameters": [
          {
            "name": "X-ID-Token",
            "in": "header",
            "required": false,
            "schema": {
              "title": "X-Id-Token",
              "type": "string",
              "nullable": true
            }
          }
        ],
        "requestBody": {
          "required": true,
          "content": {
            "application/json": {
              "schema": {
                "$ref": "#/components/schemas/RoutineStartPayload"
              }
            }
          }
        },
        "responses": {
          "202": {
            "description": "Successful Response",
            "content": {
              "application/json": {
                "schema": {}
              }
            }
          },
          "422": {
            "description": "Validation Error",
            "content": {
              "application/json": {
                "schema": {
                  "$ref": "#/components/schemas/HTTPValidationError"
                }
              }
            }
          }
        }
      }
    },
    "/api/routine-control/stop": {
      "post": {
        "tags": [
          "routine-control"
        ],
        "summary": "Stop Current Routine",
        "operationId": "stop_current_routine_api_routine_control_stop_post",
        "security": [
          {
            "OAuth2PasswordBearer": []
          }
        ],
        "parameters": [
          {
            "name": "X-ID-Token",
            "in": "header",
            "required": false,
            "schema": {
              "title": "X-Id-Token",
              "type": "string",
              "nullable": true
            }
          }
        ],
        "responses": {
          "202": {
            "description": "Successful Response",
            "content": {
              "application/json": {
                "schema": {}
              }
            }
          },
          "422": {
            "description": "Validation Error",
            "content": {
              "application/json": {
                "schema": {
                  "$ref": "#/components/schemas/HTTPValidationError"
                }
              }
            }
          }
        }
      }
    },
    "/api/friends/": {
      "get": {
        "tags": [
          "friends"
        ],
        "summary": "List Friends",
        "description": "List all accepted friends of the current user.",
        "operationId": "friends_list",
        "security": [
          {
            "OAuth2PasswordBearer": []
          }
        ],
        "parameters": [
          {
            "name": "X-ID-Token",
            "in": "header",
            "required": false,
            "schema": {
              "title": "X-Id-Token",
              "type": "string",
              "nullable": true
            }
          }
        ],
        "responses": {
          "200": {
            "description": "Successful Response",
            "content": {
              "application/json": {
                "schema": {
                  "type": "array",
                  "items": {
                    "$ref": "#/components/schemas/FriendRead"
                  },
                  "title": "Response Friends List"
                }
              }
            }
          },
          "422": {
            "description": "Validation Error",
            "content": {
              "application/json": {
                "schema": {
                  "$ref": "#/components/schemas/HTTPValidationError"
                }
              }
            }
          }
        }
      }
    },
    "/api/friends/requests": {
      "get": {
        "tags": [
          "friends"
        ],
        "summary": "List Friend Requests",
        "description": "List all pending friend requests sent TO the current user.",
        "operationId": "friends_requests_list",
        "security": [
          {
            "OAuth2PasswordBearer": []
          }
        ],
        "parameters": [
          {
            "name": "X-ID-Token",
            "in": "header",
            "required": false,
            "schema": {
              "title": "X-Id-Token",
              "type": "string",
              "nullable": true
            }
          }
        ],
        "responses": {
          "200": {
            "description": "Successful Response",
            "content": {
              "application/json": {
                "schema": {
                  "type": "array",
                  "items": {
                    "$ref": "#/components/schemas/FriendRead"
                  },
                  "title": "Response Friends Requests List"
                }
              }
            }
          },
          "422": {
            "description": "Validation Error",
            "content": {
              "application/json": {
                "schema": {
                  "$ref": "#/components/schemas/HTTPValidationError"
                }
              }
            }
          }
        }
      }
    },
    "/api/friends/add": {
      "post": {
        "tags": [
          "friends"
        ],
        "summary": "Add Friend",
        "description": "Send a friend request using a friend code.",
        "operationId": "friends_add",
        "security": [
          {
            "OAuth2PasswordBearer": []
          }
        ],
        "parameters": [
          {
            "name": "X-ID-Token",
            "in": "header",
            "required": false,
            "schema": {
              "title": "X-Id-Token",
              "type": "string",
              "nullable": true
            }
          }
        ],
        "requestBody": {
          "required": true,
          "content": {
            "application/json": {
              "schema": {
                "$ref": "#/components/schemas/FriendAdd"
              }
            }
          }
        },
        "responses": {
          "201": {
            "description": "Successful Response",
            "content": {
              "application/json": {
                "schema": {}
              }
            }
          },
          "422": {
            "description": "Validation Error",
            "content": {
              "application/json": {
                "schema": {
                  "$ref": "#/components/schemas/HTTPValidationError"
                }
              }
            }
          }
        }
      }
    },
    "/api/friends/{friend_id}/accept": {
      "post": {
        "tags": [
          "friends"
        ],
        "summary": "Accept Friend",
        "description": "Accept a friend request.",
        "operationId": "friends_accept",
        "security": [
          {
            "OAuth2PasswordBearer": []
          }
        ],
        "parameters": [
          {
            "name": "friend_id",
            "in": "path",
            "required": true,
            "schema": {
              "type": "integer",
              "title": "Friend Id"
            }
          },
          {
            "name": "X-ID-Token",
            "in": "header",
            "required": false,
            "schema": {
              "title": "X-Id-Token",
              "type": "string",
              "nullable": true
            }
          }
        ],
        "responses": {
          "200": {
            "description": "Successful Response",
            "content": {
              "application/json": {
                "schema": {}
              }
            }
          },
          "422": {
            "description": "Validation Error",
            "content": {
              "application/json": {
                "schema": {
                  "$ref": "#/components/schemas/HTTPValidationError"
                }
              }
            }
          }
        }
      }
    },
    "/api/friends/{friend_id}/decline": {
      "post": {
        "tags": [
          "friends"
        ],
        "summary": "Decline Friend",
        "description": "Decline a friend request.",
        "operationId": "friends_decline",
        "security": [
          {
            "OAuth2PasswordBearer": []
          }
        ],
        "parameters": [
          {
            "name": "friend_id",
            "in": "path",
            "required": true,
            "schema": {
              "type": "integer",
              "title": "Friend Id"
            }
          },
          {
            "name": "X-ID-Token",
            "in": "header",
            "required": false,
            "schema": {
              "title": "X-Id-Token",
              "type": "string",
              "nullable": true
            }
          }
        ],
        "responses": {
          "200": {
            "description": "Successful Response",
            "content": {
              "application/json": {
                "schema": {}
              }
            }
          },
          "422": {
            "description": "Validation Error",
            "content": {
              "application/json": {
                "schema": {
                  "$ref": "#/components/schemas/HTTPValidationError"
                }
              }
            }
          }
        }
      }
    },
    "/api/friends/{friend_id}": {
      "delete": {
        "tags": [
          "friends"
        ],
        "summary": "Remove Friend",
        "description": "Remove a friend or cancel a request.",
        "operationId": "friends_remove",
        "security": [
          {
            "OAuth2PasswordBearer": []
          }
        ],
        "parameters": [
          {
            "name": "friend_id",
            "in": "path",
            "required": true,
            "schema": {
              "type": "integer",
              "title": "Friend Id"
            }
          },
          {
            "name": "X-ID-Token",
            "in": "header",
            "required": false,
            "schema": {
              "title": "X-Id-Token",
              "type": "string",
              "nullable": true
            }
          }
        ],
        "responses": {
          "200": {
            "description": "Successful Response",
            "content": {
              "application/json": {
                "schema": {}
              }
            }
          },
          "422": {
            "description": "Validation Error",
            "content": {
              "application/json": {
                "schema": {
                  "$ref": "#/components/schemas/HTTPValidationError"
                }
              }
            }
          }
        }
      }
    }
  },
  "components": {
    "schemas": {
      "AccessLevel": {
        "type": "string",
        "enum": [
          "owner",
          "write",
          "read"
        ],
        "title": "AccessLevel"
      },
      "ActiveRoutineStatusRead": {
        "properties": {
          "active_routine_id": {
            "title": "Active Routine Id",
            "type": "integer",
            "nullable": true
          },
          "routine_name": {
            "title": "Routine Name",
            "type": "string",
            "nullable": true
          },
          "status": {
            "type": "string",
            "title": "Status"
          },
          "current_task_position": {
            "title": "Current Task Position",
            "type": "integer",
            "nullable": true
          },
          "started_at": {
            "title": "Started At",
            "type": "string",
            "format": "date-time",
            "nullable": true
          },
          "paused_at": {
            "title": "Paused At",
            "type": "string",
            "format": "date-time",
            "nullable": true
          },
          "pause_duration": {
            "type": "integer",
            "title": "Pause Duration",
            "default": 0
          }
        },
        "type": "object",
        "required": [
          "status"
        ],
        "title": "ActiveRoutineStatusRead"
      },
      "DeviceRead": {
        "properties": {
          "name": {
            "type": "string",
            "title": "Name"
          },
          "type": {
            "type": "string",
            "title": "Type"
          },
          "is_active": {
            "type": "boolean",
            "title": "Is Active",
            "default": true
          },
          "id": {
            "type": "integer",
            "title": "Id"
          },
          "status": {
            "$ref": "#/components/schemas/DeviceStatus",
            "default": "offline"
          }
        },
        "type": "object",
        "required": [
          "name",
          "type",
          "id"
        ],
        "title": "Device"
      },
      "DeviceStatus": {
        "type": "string",
        "enum": [
          "online",
          "offline"
        ],
        "title": "DeviceStatus"
      },
      "FriendAdd": {
        "properties": {
          "friend_code": {
            "type": "string",
            "title": "Friend Code"
          }
        },
        "type": "object",
        "required": [
          "friend_code"
        ],
        "title": "FriendAdd"
      },
      "FriendRead": {
        "properties": {
          "id": {
            "type": "integer",
            "title": "Id"
          },
          "username": {
            "type": "string",
            "title": "Username"
          },
          "profile_picture": {
            "title": "Profile Picture",
            "type": "string",
            "nullable": true
          },
          "status": {
            "$ref": "#/components/schemas/FriendshipStatus",
            "nullable": true
          }
        },
        "type": "object",
        "required": [
          "id",
          "username"
        ],
        "title": "FriendRead"
      },
      "FriendshipStatus": {
        "type": "string",
        "enum": [
          "pending",
          "accepted"
        ],
        "title": "FriendshipStatus"
      },
      "HTTPValidationError": {
        "properties": {
          "detail": {
            "items": {
              "$ref": "#/components/schemas/ValidationError"
            },
            "type": "array",
            "title": "Detail"
          }
        },
        "type": "object",
        "title": "HTTPValidationError"
      },
      "RoutineCreate": {
        "properties": {
          "name": {
            "type": "string",
            "title": "Name"
          },
          "description": {
            "title": "Description",
            "type": "string",
            "nullable": true
          }
        },
        "type": "object",
        "required": [
          "name"
        ],
        "title": "RoutineCreate"
      },
      "RoutineRead": {
        "properties": {
          "name": {
            "type": "string",
            "title": "Name"
          },
          "description": {
            "title": "Description",
            "type": "string",
            "nullable": true
          },
          "id": {
            "type": "integer",
            "title": "Id"
          },
          "access_level": {
            "$ref": "#/components/schemas/AccessLevel",
            "nullable": true
          },
          "start_mode": {
            "$ref": "#/components/schemas/StartMode",
            "default": "none"
          },
          "notify_mask": {
            "type": "integer",
            "title": "Notify Mask",
            "default": 0
          },
          "tasks": {
            "title": "Tasks",
            "items": {
              "$ref": "#/components/schemas/TaskInRoutineRead"
            },
            "type": "array",
            "nullable": true
          }
        },
        "type": "object",
        "required": [
          "name",
          "id"
        ],
        "title": "Routine"
      },
      "RoutineShareCreate": {
        "properties": {
          "user_id": {
            "type": "integer",
            "title": "User Id"
          },
          "access_level": {
            "$ref": "#/components/schemas/AccessLevel",
            "default": "read"
          }
        },
        "type": "object",
        "required": [
          "user_id"
        ],
        "title": "RoutineShareCreate"
      },
      "RoutineShareRead": {
        "properties": {
          "user_id": {
            "type": "integer",
            "title": "User Id"
          },
          "access_level": {
            "$ref": "#/components/schemas/AccessLevel",
            "default": "read"
          },
          "username": {
            "type": "string",
            "title": "Username"
          },
          "profile_picture": {
            "title": "Profile Picture",
            "type": "string",
            "nullable": true
          }
        },
        "type": "object",
        "required": [
          "user_id",
          "username"
        ],
        "title": "RoutineShareRead"
      },
      "RoutineShareUpdate": {
        "properties": {
          "access_level": {
            "$ref": "#/components/schemas/AccessLevel",
            "nullable": true
          }
        },
        "type": "object",
        "title": "RoutineShareUpdate"
      },
      "RoutineStartPayload": {
        "properties": {
          "name": {
            "type": "string",
            "title": "Name"
          }
        },
        "type": "object",
        "required": [
          "name"
        ],
        "title": "RoutineStartPayload"
      },
      "RoutineTaskAdd": {
        "properties": {
          "task_id": {
            "type": "integer",
            "title": "Task Id"
          },
          "position": {
            "title": "Position",
            "type": "integer",
            "nullable": true
          }
        },
        "type": "object",
        "required": [
          "task_id"
        ],
        "title": "RoutineTaskAdd"
      },
      "RoutineUpdate": {
        "properties": {
          "name": {
            "title": "Name",
            "type": "string",
            "nullable": true
          },
          "description": {
            "title": "Description",
            "type": "string",
            "nullable": true
          },
          "start_mode": {
            "$ref": "#/components/schemas/StartMode",
            "nullable": true
          },
          "notify_mask": {
            "title": "Notify Mask",
            "type": "integer",
            "nullable": true
          }
        },
        "type": "object",
        "title": "RoutineUpdate"
      },
      "StartMode": {
        "type": "string",
        "enum": [
          "none",
          "follow_owner",
          "follow_any"
        ],
        "title": "StartMode"
      },
      "TaskCreate": {
        "properties": {
          "name": {
            "type": "string",
            "title": "Name"
          },
          "icon_name": {
            "type": "string",
            "title": "Icon Name"
          },
          "sound": {
            "type": "string",
            "title": "Sound"
          },
          "duration": {
            "type": "integer",
            "title": "Duration"
          }
        },
        "type": "object",
        "required": [
          "name",
          "icon_name",
          "sound",
          "duration"
        ],
        "title": "TaskCreate"
      },
      "TaskInRoutineRead": {
        "properties": {
          "id": {
            "type": "integer",
            "title": "Id"
          },
          "name": {
            "type": "string",
            "title": "Name"
          },
          "icon_name": {
            "type": "string",
            "title": "Icon Name"
          },
          "sound": {
            "type": "string",
            "title": "Sound"
          },
          "duration": {
            "type": "integer",
            "title": "Duration"
          },
          "position": {
            "type": "integer",
            "title": "Position"
          }
        },
        "type": "object",
        "required": [
          "id",
          "name",
          "icon_name",
          "sound",
          "duration",
          "position"
        ],
        "title": "TaskInRoutineRead"
      },
      "TaskRead": {
        "properties": {
          "name": {
            "type": "string",
            "title": "Name"
          },
          "icon_name": {
            "type": "string",
            "title": "Icon Name"
          },
          "sound": {
            "type": "string",
            "title": "Sound"
          },
          "duration": {
            "type": "integer",
            "title": "Duration"
          },
          "id": {
            "type": "integer",
            "title": "Id"
          }
        },
        "type": "object",
        "required": [
          "name",
          "icon_name",
          "sound",
          "duration",
          "id"
        ],
        "title": "Task"
      },
      "TaskUpdate": {
        "properties": {
          "name": {
            "title": "Name",
            "type": "string",
            "nullable": true
          },
          "icon_name": {
            "title": "Icon Name",
            "type": "string",
            "nullable": true
          },
          "sound": {
            "title": "Sound",
            "type": "string",
            "nullable": true
          },
          "duration": {
            "title": "Duration",
            "type": "integer",
            "nullable": true
          }
        },
        "type": "object",
        "title": "TaskUpdate"
      },
      "UserRead": {
        "properties": {
          "email": {
            "title": "Email",
            "type": "string",
            "format": "email",
            "nullable": true
          },
          "username": {
            "title": "Username",
            "type": "string",
            "nullable": true
          },
          "is_active": {
            "title": "Is Active",
            "default": true,
            "type": "boolean",
            "nullable": true
          },
          "is_superuser": {
            "title": "Is Superuser",
            "default": false,
            "type": "boolean",
            "nullable": true
          },
          "oidc_sub": {
            "type": "string",
            "title": "Oidc Sub"
          },
          "friend_code": {
            "title": "Friend Code",
            "type": "string",
            "nullable": true
          },
          "profile_picture": {
            "title": "Profile Picture",
            "type": "string",
            "nullable": true
          },
          "id": {
            "type": "integer",
            "title": "Id"
          }
        },
        "type": "object",
        "required": [
          "oidc_sub",
          "id"
        ],
        "title": "UserRead",
        "description": "Schema for returning user data."
      },
      "UserUpdate": {
        "properties": {
          "profile_picture": {
            "title": "Profile Picture",
            "type": "string",
            "nullable": true
          }
        },
        "type": "object",
        "title": "UserUpdate",
        "description": "Schema for updating a user."
      },
      "ValidationError": {
        "properties": {
          "loc": {
            "items": {
              "anyOf": [
                {
                  "type": "string"
                },
                {
                  "type": "integer"
                }
              ]
            },
            "type": "array",
            "title": "Location"
          },
          "msg": {
            "type": "string",
            "title": "Message"
          },
          "type": {
            "type": "string",
            "title": "Error Type"
          }
        },
        "type": "object",
        "required": [
          "loc",
          "msg",
          "type"
        ],
        "title": "ValidationError"
      }
    },
    "securitySchemes": {
      "OAuth2PasswordBearer": {
        "type": "oauth2",
        "flows": {
          "password": {
            "scopes": {},
            "tokenUrl": "token"
          }
        }
      }
    }
  }
}